{
  "source_file": "quotation_03.pdf",
  "full_text": "御見積書\n中央オフィス機器株式会社 御中\n御No. Q-2026-0003\n〒100-0005\n発行日 2026年5月19日\n東京都千代田区丸の内1-9-1\n株式会社札幌オフィス\n₸ 060-0001\n北海道札幌市中央区北1条西3-3\nTEL: 038-259-4527\n件名\nオフィス用品納入\n納期:受注後 10 営業日\n支払条件\n納品後30日以内\n有効期限:発行日より 90 日間\nNo.\n品名\n数量\n単価\n金額\n1\nデスクライト\n4\n12,000\n48,000\n2\nトナーカートリッジ\n12\n8,500\n102,000\n3\nロッカー\n28\n45,000\n1,260,000\n小計\n1,410,000\n消費税(10%)\n141,000\n合計\n1,551,000\n御見積金額\n¥1,551,000-(税込)\n備考:\n上記金額には消費税(10%)を含みます。 :unselected:",
  "documents": [
    {
      "doc_type": "invoice",
      "confidence": 1.0,
      "vendor_name": "中央オフィス機器株式会社",
      "vendor_address": "〒100-0005\n東京都千代田区丸の内1-9-1",
      "customer_name": "株式会社札幌オフィス",
      "customer_address": "北海道札幌市中央区北1条西3-3",
      "invoice_id": "Q-2026-0003",
      "invoice_date": "2026-05-19",
      "due_date": null,
      "subtotal": 1410000.0,
      "total_tax": 141000.0,
      "invoice_total": 1551000.0,
      "items": [
        {
          "description": "デスクライト",
          "description_confidence": 0.915,
          "quantity": 4.0,
          "quantity_confidence": 0.921,
          "unitprice": 12000.0,
          "unitprice_confidence": 0.921,
          "amount": 48000.0,
          "amount_confidence": 0.921
        },
        {
          "description": "トナーカートリッジ",
          "description_confidence": 0.907,
          "quantity": 12.0,
          "quantity_confidence": 0.921,
          "unitprice": 8500.0,
          "unitprice_confidence": 0.921,
          "amount": 102000.0,
          "amount_confidence": 0.921
        },
        {
          "description": "ロッカー",
          "description_confidence": 0.92,
          "quantity": 28.0,
          "quantity_confidence": 0.921,
          "unitprice": 45000.0,
          "unitprice_confidence": 0.921,
          "amount": 1260000.0,
          "amount_confidence": 0.921
        }
      ]
    }
  ]
}